ds_event_stream_python_sdk-0.1.1.dist-info/licenses/LICENSE
dseventstream/kafka/kafka_config.py
dseventstream/kafka/kafka_service.py
dseventstream/models/event.py
dseventstream/models/system_topics.py
ds_event_stream_python_sdk-0.1.1.dist-info/METADATA
ds_event_stream_python_sdk-0.1.1.dist-info/WHEEL
ds_event_stream_python_sdk-0.1.1.dist-info/top_level.txt
ds_event_stream_python_sdk-0.1.1.dist-info/RECORD
