Metadata-Version: 2.4
Name: ds-event-stream-python-sdk
Version: 0.1.1
Summary: A modern Python SDK for Kafka event streaming (Grasp Labs)
Author-email: Grasp Labs <hello@grasplabs.no>
Maintainer-email: Grasp Labs <hello@grasplabs.no>
License-Expression: Apache-2.0
Project-URL: Homepage, https://github.com/grasp-labs/ds-event-stream-py-sdk
Project-URL: Documentation, https://grasp-labs.github.io/ds-event-stream-py-sdk/
Project-URL: Repository, https://github.com/grasp-labs/ds-event-stream-py-sdk.git
Project-URL: Issues, https://github.com/grasp-labs/ds-event-stream-py-sdk/issues
Project-URL: Changelog, https://github.com/grasp-labs/ds-event-stream-py-sdk/releases
Keywords: kafka,event-streaming,sdk,python,grasp-labs
Classifier: Development Status :: 3 - Alpha
Classifier: Intended Audience :: Developers
Classifier: Operating System :: OS Independent
Classifier: Programming Language :: Python :: 3
Classifier: Programming Language :: Python :: 3.11
Classifier: Programming Language :: Python :: 3.12
Classifier: Programming Language :: Python :: 3.13
Classifier: Topic :: Software Development :: Libraries :: Python Modules
Classifier: Topic :: System :: Distributed Computing
Requires-Python: >=3.11
License-File: LICENSE
Requires-Dist: confluent-kafka>=2.0.0
Provides-Extra: dev
Requires-Dist: datamodel-code-generator>=0.25.0; extra == "dev"
Requires-Dist: mkdocs>=1.5.0; extra == "dev"
Requires-Dist: mkdocs-material>=9.0.0; extra == "dev"
Requires-Dist: build>=0.10.0; extra == "dev"
Requires-Dist: twine>=4.0.0; extra == "dev"
Dynamic: license-file
